pyzbase32/__init__.py
pyzbase32/__main__.py
pyzbase32/ext.cpython-37m-darwin.so
pyzbase32-0.0.1.dist-info/LICENSE
pyzbase32-0.0.1.dist-info/METADATA
pyzbase32-0.0.1.dist-info/WHEEL
pyzbase32-0.0.1.dist-info/top_level.txt
pyzbase32-0.0.1.dist-info/RECORD
